Metadata-Version: 1.2
Name: baunomian
Version: 0.3
Summary: Gaussian and Binomial distribution
Home-page: UNKNOWN
Author: Tatum Roaquin
Author-email: UNKNOWN
License: MIT
Keywords: gaussian,binomial,math,distribution,statistics
Platform: UNKNOWN
Requires-Python: >=3.6.3
